geno_reader-0.1.0.dist-info/METADATA
geno_reader-0.1.0.dist-info/WHEEL
geno_reader/__init__.py
geno_reader/geno_reader.cpython-313-darwin.so
geno_reader-0.1.0.dist-info/RECORD
