Metadata-Version: 2.4
Name: geno-reader
Version: 0.1.0
Requires-Dist: maturin>=1.9.4
Requires-Dist: numpy>=2.3.0
Summary: A tool to read invididual-level genotype data.
Requires-Python: >=3.11
